[{"id": 2712, "title": "核电股早盘走高 中核国际及中广核矿业均涨超7%", "source": "新浪财经", "url": "https://finance.sina.com.cn/stock/hkstock/marketalerts/2026-06-03/doc-iniaavwy1047657.shtml", "summary": "核电股早盘走高，截至发稿，中核国际（02302）上涨7.41%，报4.93港元；中广核矿业（01164）上涨7.01%，报3.51港元。", "ts": "1780451902", "fetched": "2026-06-03 10:00:01", "date": "06-03 09:58"}, {"id": 2713, "title": "日本财务大臣片山皋月重申随时准备应对汇市波动", "source": "新浪财经", "url": "https://finance.sina.com.cn/stock/usstock/c/2026-06-03/doc-iniaavwv1011294.shtml", "summary": " 日本财务大臣片山皋月重申，当局已准备好随时根据需要对外汇市场走势作出应对。她发表上述言论之际，日元汇率再度贬至接近4月下旬政府出手干预提供支撑的水平。", "ts": "1780451595", "fetched": "2026-06-03 10:00:01", "date": "06-03 09:53"}, {"id": 2714, "title": "企业结汇需求继续释放，资金供给强于需求格局或延续", "source": "新浪财经", "url": "https://finance.sina.com.cn/money/fund/jjh/2026-06-03/doc-iniaavww4264213.shtml", "summary": "国开债ETF博时（159650）基金经理 吕瑞君 上周五（5月22日），银行间流动性边际收敛，主要资金价格有所上行，当日央行净投放1525亿元。", "ts": "1780451539", "fetched": "2026-06-03 10:00:01", "date": "06-03 09:52"}, {"id": 2715, "title": "博时基金王祥：黄金震荡加剧，美伊协议拉锯影响市场", "source": "新浪财经", "url": "https://finance.sina.com.cn/money/fund/jjh/2026-06-03/doc-iniaavwv1009285.shtml", "summary": " 上周（5.25~5.29）黄金市场震荡加剧，美伊协议拉锯影响市场通胀前景与政策预期，进而引起金价大幅波动。国内投资者边际略微流出，但幅度相对有限。", "ts": "1780451474", "fetched": "2026-06-03 10:00:01", "date": "06-03 09:51"}, {"id": 2716, "title": "博时宏观观点：AI基本面高景气但短期热度或有所透支，市场风格有望切换", "source": "新浪财经", "url": "https://finance.sina.com.cn/money/fund/jjh/2026-06-03/doc-iniaavwy1038400.shtml", "summary": "过去一个月，焦点聚焦在结构而非指数。在海外流动性风险有所改善背景下，AI基本面高景气，但短期热度或有所透支，需要时间震荡消化。", "ts": "1780451377", "fetched": "2026-06-03 10:00:01", "date": "06-03 09:49"}, {"id": 2717, "title": "资金布局券商板块 富国中证全指证券公司ETF发起式联接基金正在发行中", "source": "新浪财经", "url": "https://finance.sina.com.cn/money/fund/jjh/2026-06-03/doc-iniaavwy1033022.shtml", "summary": "近期，随着A股市场交易维持活跃，证券板块正悄然吸引投资者布局。Wind数据显示，5月申万证券II指数（801193）获融资净买入7.99亿元...", "ts": "1780451100", "fetched": "2026-06-03 10:00:01", "date": "06-03 09:45"}, {"id": 2718, "title": "震荡市中FOF备受关注 银华华瑞多元配置三个月持有期混合（FOF）今起发行", "source": "新浪财经", "url": "https://finance.sina.com.cn/money/fund/jjh/2026-06-03/doc-iniaavwy1031779.shtml", "summary": "震荡市中，FOF产品成为投资者关注焦点之一。据统计，当前FOF总规模已突破3500亿元，年内新增规模突破1000亿元。银华基金旗下FOF序列再出精品——银华华瑞多元配置三个月持有...", "ts": "1780451044", "fetched": "2026-06-03 10:00:01", "date": "06-03 09:44"}, {"id": 2719, "title": "不押注单一赛道，多基金经理共管实践的体系制胜", "source": "新浪财经", "url": "https://finance.sina.com.cn/money/fund/jjh/2026-06-03/doc-iniaavwu2533675.shtml", "summary": " 近些年来，在A股市场快速轮动、赛道行情大起大落的环境下，投资者最真切的感受莫过那些押注单一方向的产品，往往涨得迅猛、跌得也惊心。", "ts": "1780450950", "fetched": "2026-06-03 10:00:01", "date": "06-03 09:42"}, {"id": 2720, "title": "华泰期货：锌涨价抑制现货活跃度", "source": "新浪财经", "url": "https://finance.sina.com.cn/money/future/fmnews/2026-06-03/doc-iniaavwy1026355.shtml", "summary": "来源：华泰期货 作者： 封帆 重要数据 现货方面：LME锌现货升水为-21.66美元/吨。SMM上海锌现货价较前一交易日变化10元/吨至24720元/吨...", "ts": "1780450779", "fetched": "2026-06-03 10:00:01", "date": "06-03 09:39"}, {"id": 2721, "title": "华泰期货：沪锡近日走强，“算力叙事”催化市场情绪", "source": "新浪财经", "url": "https://finance.sina.com.cn/money/future/fmnews/2026-06-03/doc-iniaavwu2528280.shtml", "summary": "来源：华泰期货 作者： 新能源有色金属组 沪锡昨日明显走强，主力合约沪锡2607收于44.98万元/吨，涨幅达5.19%。供应端扰动叠加基于半导体行情的情绪催化...", "ts": "1780450632", "fetched": "2026-06-03 10:00:01", "date": "06-03 09:37"}, {"id": 2722, "title": "鸿星科技IPO：林氏家族控股近88%，递表前分红5.69亿", "source": "新浪财经", "url": "https://finance.sina.com.cn/money/fund/etf/2026-06-03/doc-iniaavwy1021848.shtml", "summary": "来源：瑞财经 瑞财经严明会5月12日，鸿星科技（集团）股份有限公司（以下简称：鸿星科技）深交所创业板IPO获受理，保荐机构为国投证券，保荐代表人为俞高平、钱润...", "ts": "1780450532", "fetched": "2026-06-03 10:00:01", "date": "06-03 09:35"}, {"id": 2723, "title": "世界气象组织拉响警报：6-8月发生厄尔尼诺事件概率高达80%", "source": "新浪财经", "url": "https://finance.sina.com.cn/jjxw/2026-06-03/doc-iniaavwv0995849.shtml", "summary": "来源：财联社 财联社6月3日讯（编辑 潇湘）世界气象组织（WMO）周二表示，受热带太平洋异常温暖海水的驱动，厄尔尼诺气象模式正在形成，预计今年将在全球引发极端天气。", "ts": "1780450500", "fetched": "2026-06-03 10:00:01", "date": "06-03 09:35"}, {"id": 2724, "title": "华泰期货：泰国原料价格继续上行，橡胶成本端支撑加强", "source": "新浪财经", "url": "https://finance.sina.com.cn/money/future/fmnews/2026-06-03/doc-iniaavww4242823.shtml", "summary": "来源：华泰期货 作者： 陈莉 市场要闻与数据 期货方面，昨日收盘RU主力合约18170元/吨，较前一日变动+105元/吨；NR主力合约15760元/吨...", "ts": "1780450492", "fetched": "2026-06-03 10:00:01", "date": "06-03 09:34"}, {"id": 2725, "title": "华泰期货：现货货源相对偏紧 铜价震荡偏强", "source": "新浪财经", "url": "https://finance.sina.com.cn/money/future/fmnews/2026-06-03/doc-iniaavwy1015984.shtml", "summary": "来源：华泰期货 作者： 师橙 市场要闻与重要数据 期货行情： 2026-06-02，沪铜主力合约开于 105850元/吨，收于 106620元/吨，较前一交易日收盘1.85%...", "ts": "1780450308", "fetched": "2026-06-03 10:00:01", "date": "06-03 09:31"}, {"id": 2697, "title": "金斯瑞生物科技高开近15% 传奇生物披露治疗淋巴瘤初步临床数据显示积极信号", "source": "新浪财经", "url": "https://finance.sina.com.cn/stock/hkstock/marketalerts/2026-06-03/doc-iniaavwv0986613.shtml", "summary": "金斯瑞生物科技（01548）早盘高开近15%，截至发稿，股价上涨14.99%，现报13.96港元，成交额617.03万港元。 隔夜美股传奇生物暴涨超42%，最新市值67亿美元。", "ts": "1780450085", "fetched": "2026-06-03 09:30:01", "date": "06-03 09:28"}, {"id": 2698, "title": "稀美资源拟先旧后新配售最多3410万股 净筹约5.372亿港元", "source": "新浪财经", "url": "https://finance.sina.com.cn/stock/hkstock/ggscyd/2026-06-03/doc-iniaavwu2518019.shtml", "summary": "稀美资源（09936）发布公告，于2026年6月2日，公司、卖方及联席配售代理订立配售及认购协议，据此，（i）卖方已同意出售，而联席配售代理已有条件同意担任卖方的代理...", "ts": "1780449981", "fetched": "2026-06-03 09:30:01", "date": "06-03 09:26"}, {"id": 2699, "title": "三环集团多个关键“卡脖子”环节实现国产替代 MLCC“通胀”叙事有无透支股价", "source": "新浪财经", "url": "https://finance.sina.com.cn/stock/observe/2026-06-03/doc-iniaavwy1009905.shtml", "summary": "出品：新浪财经上市公司研究院 文/夏虫工作室 核心观点：MLCC行业因AI服务器（用量激增）和汽车电动化（单车用量6倍）需求爆发，叠加高端产能扩张慢...", "ts": "1780449930", "fetched": "2026-06-03 09:30:01", "date": "06-03 09:25"}, {"id": 2700, "title": "智数科技集团拟折让约10.00%配售最多2830万股 净筹约4990万港元", "source": "新浪财经", "url": "https://finance.sina.com.cn/stock/hkstock/ggscyd/2026-06-03/doc-iniaavww4232537.shtml", "summary": "智数科技集团（01159）发布公告，于2026年6月2日（交易时段后），本公司与配售代理订立配售协议，据此，本公司委任配售代理（作为本公司的独家代理）尽最大努力于配售事项...", "ts": "1780449919", "fetched": "2026-06-03 09:30:01", "date": "06-03 09:25"}, {"id": 2701, "title": "中信建投期货：6月3日能化早报", "source": "新浪财经", "url": "https://finance.sina.com.cn/money/future/fmnews/2026-06-03/doc-iniaavww4231500.shtml", "summary": "橡胶：供应释放预期持续 周三，国产全乳胶 17400/吨，环比上日持平；泰国 20 号混合胶 16950 元/吨，环比上日持平。 原料端：泰国胶水报收 83.7 泰铢/公斤...", "ts": "1780449849", "fetched": "2026-06-03 09:30:01", "date": "06-03 09:24"}, {"id": 2702, "title": "华泰期货：下游情绪谨慎，玻碱盘面偏弱", "source": "新浪财经", "url": "https://finance.sina.com.cn/money/future/fmnews/2026-06-03/doc-iniaavwy1007558.shtml", "summary": "市场分析 玻璃方面：昨日玻璃期货震荡偏弱运行。现货方面，交投氛围一般，市场以刚需为主。 供需与逻辑：目前玻璃产能小幅回升，整体日熔量依旧处于低位，行业大面积亏损...", "ts": "1780449775", "fetched": "2026-06-03 09:30:01", "date": "06-03 09:22"}]