[{"id": 2010, "title": "特朗普接受年度体检 称结果“很完美”", "source": "新浪财经", "url": "https://finance.sina.com.cn/stock/usstock/c/2026-05-27/doc-inhzikrq8474299.shtml", "summary": "美国总统唐纳德・特朗普于周二前往沃尔特・里德国家军事医疗中心接受年度体检。 特朗普在医疗中心停留了三小时，进行了预防性体检与牙科检查...", "ts": "1779863356", "fetched": "2026-05-27 14:30:02", "date": "05-27 14:29"}, {"id": 2011, "title": "欧元区发债主体转向非欧元债券，以求开拓新投资者群体", "source": "新浪财经", "url": "https://finance.sina.com.cn/stock/usstock/c/2026-05-27/doc-inhzikrs9316237.shtml", "summary": "欧元区债券市场供给持续高企，为拓展投资者群体，区内各国正大幅增加外币发债规模。 数据显示，今年迄今为止，欧元区主权国家已发行46亿美元非欧元计价债券...", "ts": "1779863335", "fetched": "2026-05-27 14:30:02", "date": "05-27 14:28"}, {"id": 2012, "title": "陈彦斌：低空经济等新兴支柱产业前景广阔，大有可为", "source": "新浪财经", "url": "https://finance.sina.com.cn/hy/hyjz/2026-05-27/doc-inhzikrq8473255.shtml", "summary": " 2026低空经济产业高质量发展大会于5月27日在北京举办，主题为“空域赋能 聚势而强”。中国社会科学院工业经济研究所所长党委副书记陈彦斌出席并致辞。", "ts": "1779863175", "fetched": "2026-05-27 14:30:02", "date": "05-27 14:26"}, {"id": 2013, "title": "招商证券：农夫山泉维持“强烈推荐” 评级 目标价55港元", "source": "新浪财经", "url": "https://finance.sina.com.cn/stock/hkstock/hkgg/2026-05-27/doc-inhzikrs0847139.shtml", "summary": "招商证券发布研报称，农夫山泉（09633）股东会指引积极，新品不断催化，动销表现有支撑，进入旺季有望迎来催化。该行维持26-28年每股收益至1.60元、1.78元、1.99元...", "ts": "1779863075", "fetched": "2026-05-27 14:30:02", "date": "05-27 14:24"}, {"id": 2014, "title": "中金：名创优品维持跑赢行业评级 目标价39.16港元", "source": "新浪财经", "url": "https://finance.sina.com.cn/stock/hkstock/hkgg/2026-05-27/doc-inhzikrs0846502.shtml", "summary": "中金发布研报称，维持名创优品（09896，MNSO.US）2026/27年经调整净利润预测31/35亿元不变，当前港/美股均对应9/9倍2026/27年经调整P/E，维持跑赢行业评级和目标价39...", "ts": "1779862985", "fetched": "2026-05-27 14:30:02", "date": "05-27 14:23"}, {"id": 2015, "title": "三星达成人工智能利润分成协议，员工人均将获 40 万美元奖金", "source": "新浪财经", "url": "https://finance.sina.com.cn/stock/usstock/c/2026-05-27/doc-inhzikrq8472019.shtml", "summary": " 三星电子员工表决通过一项具有里程碑意义的利润分成协议。受益于存储芯片业务的蓬勃发展，该部门员工人均奖金预计接近40万美元。", "ts": "1779862968", "fetched": "2026-05-27 14:30:02", "date": "05-27 14:22"}, {"id": 2016, "title": "低位制药板块韧性凸显，华宝基金药ETF（562050）午后逆市拉升！权重股恒瑞医药冲高4%，中药龙头集体飘红", "source": "新浪财经", "url": "https://finance.sina.com.cn/money/fund/etf/2026-05-27/doc-inhzikrs0846612.shtml", "summary": "5月27日午后，A股突发跳水，沪指失守4100点。制药板块局部异动，权重龙头恒瑞医药快速拉升翻红，一度冲高超4%；中药股逆市表现，云南白药、以岭药业、东阿阿胶...", "ts": "1779862964", "fetched": "2026-05-27 14:30:02", "date": "05-27 14:22"}, {"id": 2017, "title": "标的指数近1年暴涨143%！双创50ETF华宝（588330）刷新上市高点！机构：大波段行情未结束，蓄力再出发！", "source": "新浪财经", "url": "https://finance.sina.com.cn/money/fund/etf/2026-05-27/doc-inhzikrs9313792.shtml", "summary": "今日（5月27日）创业板指早盘一度涨超2.5%创历史新高，午后跳水翻绿，覆盖创业板+科创板50只高成长龙头的硬科技宽基——双创50ETF华宝（588330）场内涨幅早盘上探2.34%...", "ts": "1779862923", "fetched": "2026-05-27 14:30:02", "date": "05-27 14:22"}, {"id": 2018, "title": "高盛：渣打集团重申“买入”评级 目标价维持242港元", "source": "新浪财经", "url": "https://finance.sina.com.cn/wm/2026-05-27/doc-inhzikrs9313408.shtml", "summary": "高盛发布研报称，更新对渣打集团（02888）的预测。此前渣打在5月19日至21日的投资者日活动中，重申了2026年目标，概述多项关键结构性趋势，并订立了新的2028年目标。", "ts": "1779862903", "fetched": "2026-05-27 14:30:02", "date": "05-27 14:21"}, {"id": 2019, "title": "韩国半导体产业人员成婚恋市场宠儿", "source": "新浪财经", "url": "https://finance.sina.com.cn/stock/hyyj/2026-05-27/doc-inhzikrs0848210.shtml", "summary": " 新华社北京5月27日电 韩国半导体产业近来发展势头强劲，其从业人员不仅收入水涨船高，还有个额外收获——成为婚恋市场宠儿。", "ts": "1779862849", "fetched": "2026-05-27 14:30:02", "date": "05-27 14:20"}, {"id": 2020, "title": "博泰车联午后涨近10% AI大模型正加速向车端部署落地", "source": "新浪财经", "url": "https://finance.sina.com.cn/stock/hkstock/marketalerts/2026-05-27/doc-inhzikrs0845490.shtml", "summary": "博泰车联（02889）盘中涨超11%，月内累计涨幅超60%。截至发稿，股价上涨9.76%，现报219.40港元，成交额1.51亿港元。 博泰车联此前宣布...", "ts": "1779862836", "fetched": "2026-05-27 14:30:02", "date": "05-27 14:20"}, {"id": 2021, "title": "MINIMAX-W午后涨超5% 公司获纳入恒生科技指数", "source": "新浪财经", "url": "https://finance.sina.com.cn/stock/hkstock/marketalerts/2026-05-27/doc-inhzikrp1693004.shtml", "summary": "MINIMAX-W（00100）盘中一度涨超11%，截至发稿，股价上涨5.66%，现报812.50港元，成交额22.38亿港元。 5月22日，恒生指数公司发布季检结果，其中...", "ts": "1779862650", "fetched": "2026-05-27 14:30:02", "date": "05-27 14:17"}, {"id": 2022, "title": "央行今日在香港成功发行两期共计300亿元央票", "source": "新浪财经", "url": "https://finance.sina.com.cn/jryx/bank/2026-05-27/doc-inhzikrq8469204.shtml", "summary": "5月27日金融一线消息，人民银行于本周三（5月27日）通过香港金融管理局债务工具中央结算系统（CMU）债券投标平台，以利率招标方式发行了2026年第四期和第五期央行票据。", "ts": "1779862513", "fetched": "2026-05-27 14:30:02", "date": "05-27 14:15"}, {"id": 2023, "title": "买生鲜遇到食品安全问题该怎么维权", "source": "新浪财经", "url": "https://finance.sina.com.cn/consume/xiaofei/2026-05-27/doc-inhzhxzt1752419.shtml", "summary": "最近，盒马因为粉木耳产品问题登上热搜，随后发布致歉声明并下架相关产品。这件事再次把生鲜电商的食品安全问题推到了消费者面前。", "ts": "1779862464", "fetched": "2026-05-27 14:30:02", "date": "05-27 14:14"}, {"id": 2024, "title": "绝地反击！白酒龙头午后狂飙，华宝基金食品饮料ETF（515710）盘中涨超2%！主力逆市加码", "source": "新浪财经", "url": "https://finance.sina.com.cn/money/fund/etf/2026-05-27/doc-inhzikrq8468718.shtml", "summary": "吃喝板块今日（5月27日）上演惊天逆转！反映吃喝板块整体走势的食品饮料ETF华宝（515710）早盘一度跌超2%，午后突然猛拉，盘中场内价格最高涨幅达到2.16%，截至发稿，涨1...", "ts": "1779862449", "fetched": "2026-05-27 14:30:02", "date": "05-27 14:14"}, {"id": 1995, "title": "视频丨净利骤降近九成、全国化“折戟”，天佑德酒业绩说明会坦言：营销能力有限，对股价“非常惭愧”", "source": "新浪财经", "url": "https://finance.sina.com.cn/stock/companyt/2026-05-27/doc-inhzikrs0812630.shtml", "summary": "", "ts": "1779859566", "fetched": "2026-05-27 13:30:01", "date": "05-27 13:26"}, {"id": 1996, "title": "视频丨再融资“狼来了”？中国平安又要融资500亿，借钱也要给股东分红?", "source": "新浪财经", "url": "https://finance.sina.com.cn/stock/companyt/2026-05-27/doc-inhzieiu9408744.shtml", "summary": "", "ts": "1779859323", "fetched": "2026-05-27 13:30:01", "date": "05-27 13:22"}, {"id": 1997, "title": "视频丨二股东一年三次卖安凯客车，公司扣非十年亏近28亿元，反腐刚揪出三名营销高管", "source": "新浪财经", "url": "https://finance.sina.com.cn/stock/companyt/2026-05-27/doc-inhzieiu0940327.shtml", "summary": "", "ts": "1779859228", "fetched": "2026-05-27 13:30:01", "date": "05-27 13:20"}, {"id": 1998, "title": "AI的尽头：不是模型，而是电厂", "source": "新浪财经", "url": "https://finance.sina.com.cn/jjxw/2026-05-27/doc-inhzieir1786643.shtml", "summary": " 碳基需求正在给硅基需求让步，硅基不光需要GPU，而且对电力胃口已经超过碳基需求，从过去两周最新消息来看，“电力”以前所未有的密度涌进硅谷AI行业头版。", "ts": "1779859179", "fetched": "2026-05-27 13:30:01", "date": "05-27 13:19"}, {"id": 1999, "title": "网上买生鲜靠不靠谱 下单前先查一查再决定", "source": "新浪财经", "url": "https://finance.sina.com.cn/consume/xiaofei/2026-05-27/doc-inhzhxzw0928193.shtml", "summary": "最近，盒马因为粉木耳产品质量问题登上热搜，官方随后发布致歉声明并下架了相关产品。这件事让不少习惯在生鲜App上买菜的人心里打了个问号：平时图方便手机上下单...", "ts": "1779858895", "fetched": "2026-05-27 13:30:01", "date": "05-27 13:14"}]