{"pools": [{"name": "糖果池", "emoji": "💎", "desc": "现金牛资产 - 可口可乐型", "ratio": 0.55, "stocks": [{"name": "长江电力", "code": "sh600900", "price": 27.69, "change_pct": -0.21621621621621162, "open": 27.74, "high": 27.87, "low": 27.55, "prev_close": 27.75, "volume": 107549118.0, "pe": 18.78, "score": 9, "reason": "水电龙头，股息率>4%，ROE>15%，永续经营", "target_weight": 0.1}, {"name": "中国神华", "code": "sh601088", "price": 48.24, "change_pct": 2.8132992327365733, "open": 47.0, "high": 49.01, "low": 47.0, "prev_close": 46.92, "volume": 39451978.0, "pe": 20.29, "score": 8, "reason": "煤炭现金牛，高分红，FCF/净利润>80%", "target_weight": 0.08}, {"name": "贵州茅台", "code": "sh600519", "price": 1307.19, "change_pct": -1.4185520361990909, "open": 1327.0, "high": 1327.0, "low": 1301.31, "prev_close": 1326.0, "volume": 3371734.0, "pe": 19.76, "score": 9, "reason": "护城河极深，毛利率>90%", "target_weight": 0.07}, {"name": "五粮液", "code": "sz000858", "price": 83.21, "change_pct": -1.9790316880669183, "open": 83.95, "high": 83.95, "low": 82.83, "prev_close": 84.89, "volume": 21294427.0, "pe": 25.63, "score": 6, "reason": "白酒老二，PE底部拐点，Q3修复预期", "target_weight": 0.06}, {"name": "中国移动", "code": "sh600941", "price": 98.8, "change_pct": -0.3027245206861727, "open": 98.8, "high": 99.1, "low": 98.2, "prev_close": 99.1, "volume": 5426534.0, "pe": 15.76, "score": 8, "reason": "电信垄断，股息>5%，9亿用户", "target_weight": 0.07}, {"name": "工商银行", "code": "sh601398", "price": 7.25, "change_pct": 0.4155124653739647, "open": 7.2, "high": 7.26, "low": 7.18, "prev_close": 7.22, "volume": 205223501.0, "pe": 6.95, "score": 8, "reason": "宇宙行股息>6%，PE仅6.9", "target_weight": 0.06}, {"name": "招商银行", "code": "sh600036", "price": 38.1, "change_pct": 0.2367797947908535, "open": 38.0, "high": 38.15, "low": 37.8, "prev_close": 38.01, "volume": 67473727.0, "pe": 6.37, "score": 7, "reason": "最佳零售银行，ROE领跑大行", "target_weight": 0.04}, {"name": "粤高速Ａ", "code": "sz000429", "price": 14.05, "change_pct": 0.285510349750185, "open": 14.0, "high": 14.11, "low": 13.66, "prev_close": 14.01, "volume": 5855401.0, "pe": 18.41, "score": 7, "reason": "路产现金牛，永续收费，高分红", "target_weight": 0.03}, {"name": "中国石油", "code": "sh601857", "price": 10.75, "change_pct": -1.1039558417663222, "open": 10.85, "high": 10.99, "low": 10.73, "prev_close": 10.87, "volume": 141882175.0, "pe": 12.44, "score": 7, "reason": "能源安全+高分红，油价支撑", "target_weight": 0.03}, {"name": "中国平安", "code": "sh601318", "price": 53.85, "change_pct": 0.6542056074766381, "open": 53.49, "high": 54.1, "low": 53.15, "prev_close": 53.5, "volume": 57245751.0, "pe": 7.34, "score": 6, "reason": "保险龙头复苏，利率回升受益", "target_weight": 0.03}]}, {"name": "火箭池", "emoji": "🚀", "desc": "成熟成长龙头 - 比亚迪型", "ratio": 0.34, "stocks": [{"name": "中际旭创", "code": "sz300308", "price": 1146.12, "change_pct": -1.2952564676702771, "open": 1161.0, "high": 1183.61, "low": 1113.9, "prev_close": 1161.16, "volume": 21924399.0, "pe": 85.48, "score": 8, "reason": "800G光模块全球龙头，AI算力刚需", "target_weight": 0.06}, {"name": "国电南瑞", "code": "sh600406", "price": 24.97, "change_pct": 0.28112449799196904, "open": 24.96, "high": 25.46, "low": 24.92, "prev_close": 24.9, "volume": 75491236.0, "pe": 24.09, "score": 7, "reason": "电网智能化龙头，十五五投资周期", "target_weight": 0.05}, {"name": "海光信息", "code": "sh688041", "price": 283.25, "change_pct": -3.623681524327995, "open": 299.77, "high": 300.19, "low": 280.0, "prev_close": 293.9, "volume": 28709909.0, "pe": 241.72, "score": 7, "reason": "国产CPU/DCU，信创替代核心", "target_weight": 0.05}, {"name": "寒武纪", "code": "sh688256", "price": 1253.03, "change_pct": -4.348854961832063, "open": 1326.0, "high": 1326.0, "low": 1241.01, "prev_close": 1310.0, "volume": 10044592.0, "pe": 289.76, "score": 5, "reason": "AI芯片唯一性但PE=280估值极高，严控仓位", "target_weight": 0.04}, {"name": "比亚迪", "code": "sz002594", "price": 94.01, "change_pct": -2.2561863173216903, "open": 96.18, "high": 96.22, "low": 94.0, "prev_close": 96.18, "volume": 31035675.0, "pe": 31.12, "score": 9, "reason": "全球EV销量冠军，全产业链垂直整合", "target_weight": 0.05}, {"name": "宁德时代", "code": "sz300750", "price": 425.11, "change_pct": 0.26179245283019187, "open": 432.1, "high": 438.24, "low": 423.6, "prev_close": 424.0, "volume": 29148255.0, "pe": 24.91, "score": 9, "reason": "电池全球40%份额，技术壁垒极深", "target_weight": 0.04}, {"name": "兆易创新", "code": "sh603986", "price": 472.0, "change_pct": 1.0684996038628742, "open": 476.0, "high": 489.96, "low": 455.0, "prev_close": 467.01, "volume": 40452462.0, "pe": 115.12, "score": 5, "reason": "🦥最懒方案: 存储芯片量价齐升+长鑫IPO影子股，PE=97须严控仓位，回调340-360才建仓，止损300", "target_weight": 0.05}]}, {"name": "种子池", "emoji": "🌱", "desc": "高赔率种子 - 拓荒型", "ratio": 0.11, "stocks": [{"name": "三花智控", "code": "sz002050", "price": 45.53, "change_pct": -1.7479499352611183, "open": 46.34, "high": 47.0, "low": 44.91, "prev_close": 46.34, "volume": 102728399.0, "pe": 46.87, "score": 5, "reason": "热管理+机器人关节，特斯拉链", "target_weight": 0.05}, {"name": "拓普集团", "code": "sh601689", "price": 62.21, "change_pct": -0.30448717948717585, "open": 62.4, "high": 63.45, "low": 61.4, "prev_close": 62.4, "volume": 22884512.0, "pe": 39.09, "score": 5, "reason": "底盘+机器人执行器，量产待确认", "target_weight": 0.05}, {"name": "许继电气", "code": "sz000400", "price": 27.02, "change_pct": 1.5026296018031502, "open": 26.98, "high": 27.29, "low": 26.8, "prev_close": 26.62, "volume": 23366014.0, "pe": 25.71, "score": 6, "reason": "特高压柔直，电网投资长周期", "target_weight": 0.03}, {"name": "航天晨光", "code": "sh600501", "price": 18.72, "change_pct": 2.2950819672131044, "open": 18.21, "high": 18.84, "low": 18.15, "prev_close": 18.3, "volume": 4094300.0, "pe": -39.01, "score": 3, "reason": "⚠️ PE=-47亏损！商业航天暂只观察，严止损-30%", "target_weight": 0.02}]}], "flat": [{"name": "长江电力", "code": "sh600900", "price": 27.69, "change_pct": -0.21621621621621162, "open": 27.74, "high": 27.87, "low": 27.55, "prev_close": 27.75, "volume": 107549118.0, "pe": 18.78, "score": 9, "reason": "水电龙头，股息率>4%，ROE>15%，永续经营", "target_weight": 0.1, "pool": "糖果池", "pool_emoji": "💎"}, {"name": "中国神华", "code": "sh601088", "price": 48.24, "change_pct": 2.8132992327365733, "open": 47.0, "high": 49.01, "low": 47.0, "prev_close": 46.92, "volume": 39451978.0, "pe": 20.29, "score": 8, "reason": "煤炭现金牛，高分红，FCF/净利润>80%", "target_weight": 0.08, "pool": "糖果池", "pool_emoji": "💎"}, {"name": "贵州茅台", "code": "sh600519", "price": 1307.19, "change_pct": -1.4185520361990909, "open": 1327.0, "high": 1327.0, "low": 1301.31, "prev_close": 1326.0, "volume": 3371734.0, "pe": 19.76, "score": 9, "reason": "护城河极深，毛利率>90%", "target_weight": 0.07, "pool": "糖果池", "pool_emoji": "💎"}, {"name": "五粮液", "code": "sz000858", "price": 83.21, "change_pct": -1.9790316880669183, "open": 83.95, "high": 83.95, "low": 82.83, "prev_close": 84.89, "volume": 21294427.0, "pe": 25.63, "score": 6, "reason": "白酒老二，PE底部拐点，Q3修复预期", "target_weight": 0.06, "pool": "糖果池", "pool_emoji": "💎"}, {"name": "中国移动", "code": "sh600941", "price": 98.8, "change_pct": -0.3027245206861727, "open": 98.8, "high": 99.1, "low": 98.2, "prev_close": 99.1, "volume": 5426534.0, "pe": 15.76, "score": 8, "reason": "电信垄断，股息>5%，9亿用户", "target_weight": 0.07, "pool": "糖果池", "pool_emoji": "💎"}, {"name": "工商银行", "code": "sh601398", "price": 7.25, "change_pct": 0.4155124653739647, "open": 7.2, "high": 7.26, "low": 7.18, "prev_close": 7.22, "volume": 205223501.0, "pe": 6.95, "score": 8, "reason": "宇宙行股息>6%，PE仅6.9", "target_weight": 0.06, "pool": "糖果池", "pool_emoji": "💎"}, {"name": "招商银行", "code": "sh600036", "price": 38.1, "change_pct": 0.2367797947908535, "open": 38.0, "high": 38.15, "low": 37.8, "prev_close": 38.01, "volume": 67473727.0, "pe": 6.37, "score": 7, "reason": "最佳零售银行，ROE领跑大行", "target_weight": 0.04, "pool": "糖果池", "pool_emoji": "💎"}, {"name": "粤高速Ａ", "code": "sz000429", "price": 14.05, "change_pct": 0.285510349750185, "open": 14.0, "high": 14.11, "low": 13.66, "prev_close": 14.01, "volume": 5855401.0, "pe": 18.41, "score": 7, "reason": "路产现金牛，永续收费，高分红", "target_weight": 0.03, "pool": "糖果池", "pool_emoji": "💎"}, {"name": "中国石油", "code": "sh601857", "price": 10.75, "change_pct": -1.1039558417663222, "open": 10.85, "high": 10.99, "low": 10.73, "prev_close": 10.87, "volume": 141882175.0, "pe": 12.44, "score": 7, "reason": "能源安全+高分红，油价支撑", "target_weight": 0.03, "pool": "糖果池", "pool_emoji": "💎"}, {"name": "中国平安", "code": "sh601318", "price": 53.85, "change_pct": 0.6542056074766381, "open": 53.49, "high": 54.1, "low": 53.15, "prev_close": 53.5, "volume": 57245751.0, "pe": 7.34, "score": 6, "reason": "保险龙头复苏，利率回升受益", "target_weight": 0.03, "pool": "糖果池", "pool_emoji": "💎"}, {"name": "中际旭创", "code": "sz300308", "price": 1146.12, "change_pct": -1.2952564676702771, "open": 1161.0, "high": 1183.61, "low": 1113.9, "prev_close": 1161.16, "volume": 21924399.0, "pe": 85.48, "score": 8, "reason": "800G光模块全球龙头，AI算力刚需", "target_weight": 0.06, "pool": "火箭池", "pool_emoji": "🚀"}, {"name": "国电南瑞", "code": "sh600406", "price": 24.97, "change_pct": 0.28112449799196904, "open": 24.96, "high": 25.46, "low": 24.92, "prev_close": 24.9, "volume": 75491236.0, "pe": 24.09, "score": 7, "reason": "电网智能化龙头，十五五投资周期", "target_weight": 0.05, "pool": "火箭池", "pool_emoji": "🚀"}, {"name": "海光信息", "code": "sh688041", "price": 283.25, "change_pct": -3.623681524327995, "open": 299.77, "high": 300.19, "low": 280.0, "prev_close": 293.9, "volume": 28709909.0, "pe": 241.72, "score": 7, "reason": "国产CPU/DCU，信创替代核心", "target_weight": 0.05, "pool": "火箭池", "pool_emoji": "🚀"}, {"name": "寒武纪", "code": "sh688256", "price": 1253.03, "change_pct": -4.348854961832063, "open": 1326.0, "high": 1326.0, "low": 1241.01, "prev_close": 1310.0, "volume": 10044592.0, "pe": 289.76, "score": 5, "reason": "AI芯片唯一性但PE=280估值极高，严控仓位", "target_weight": 0.04, "pool": "火箭池", "pool_emoji": "🚀"}, {"name": "比亚迪", "code": "sz002594", "price": 94.01, "change_pct": -2.2561863173216903, "open": 96.18, "high": 96.22, "low": 94.0, "prev_close": 96.18, "volume": 31035675.0, "pe": 31.12, "score": 9, "reason": "全球EV销量冠军，全产业链垂直整合", "target_weight": 0.05, "pool": "火箭池", "pool_emoji": "🚀"}, {"name": "宁德时代", "code": "sz300750", "price": 425.11, "change_pct": 0.26179245283019187, "open": 432.1, "high": 438.24, "low": 423.6, "prev_close": 424.0, "volume": 29148255.0, "pe": 24.91, "score": 9, "reason": "电池全球40%份额，技术壁垒极深", "target_weight": 0.04, "pool": "火箭池", "pool_emoji": "🚀"}, {"name": "兆易创新", "code": "sh603986", "price": 472.0, "change_pct": 1.0684996038628742, "open": 476.0, "high": 489.96, "low": 455.0, "prev_close": 467.01, "volume": 40452462.0, "pe": 115.12, "score": 5, "reason": "🦥最懒方案: 存储芯片量价齐升+长鑫IPO影子股，PE=97须严控仓位，回调340-360才建仓，止损300", "target_weight": 0.05, "pool": "火箭池", "pool_emoji": "🚀"}, {"name": "三花智控", "code": "sz002050", "price": 45.53, "change_pct": -1.7479499352611183, "open": 46.34, "high": 47.0, "low": 44.91, "prev_close": 46.34, "volume": 102728399.0, "pe": 46.87, "score": 5, "reason": "热管理+机器人关节，特斯拉链", "target_weight": 0.05, "pool": "种子池", "pool_emoji": "🌱"}, {"name": "拓普集团", "code": "sh601689", "price": 62.21, "change_pct": -0.30448717948717585, "open": 62.4, "high": 63.45, "low": 61.4, "prev_close": 62.4, "volume": 22884512.0, "pe": 39.09, "score": 5, "reason": "底盘+机器人执行器，量产待确认", "target_weight": 0.05, "pool": "种子池", "pool_emoji": "🌱"}, {"name": "许继电气", "code": "sz000400", "price": 27.02, "change_pct": 1.5026296018031502, "open": 26.98, "high": 27.29, "low": 26.8, "prev_close": 26.62, "volume": 23366014.0, "pe": 25.71, "score": 6, "reason": "特高压柔直，电网投资长周期", "target_weight": 0.03, "pool": "种子池", "pool_emoji": "🌱"}, {"name": "航天晨光", "code": "sh600501", "price": 18.72, "change_pct": 2.2950819672131044, "open": 18.21, "high": 18.84, "low": 18.15, "prev_close": 18.3, "volume": 4094300.0, "pe": -39.01, "score": 3, "reason": "⚠️ PE=-47亏损！商业航天暂只观察，严止损-30%", "target_weight": 0.02, "pool": "种子池", "pool_emoji": "🌱"}]}