{
  "update_time": "2026-05-29 13:50:00",
  "summary": {
    "total_assets": 122569.66,
    "cash": 97431.66,
    "cash_pct": 79.5,
    "market_value": 25534.0,
    "total_pnl": 396.0,
    "total_pnl_pct": 1.5753043201527595,
    "holding_count": 3,
    "peak_assets": 100000,
    "drawdown_pct": 0,
    "total_injected": 15000.0,
    "total_commission": 35.0
  },
  "holdings": [
    {
      "code": "600406",
      "name": "国电南瑞",
      "shares": 200,
      "avg_cost": 25.9,
      "cost": 5180.0,
      "current_price": 25.04,
      "market_value": 5008.0,
      "pnl": -172.0,
      "pnl_pct": -3.3204633204633183,
      "type": "growth",
      "sector": "电力设备"
    },
    {
      "code": "600900",
      "name": "长江电力",
      "shares": 400,
      "avg_cost": 27.1,
      "cost": 10840.0,
      "current_price": 27.67,
      "market_value": 11068.0,
      "pnl": 228.0,
      "pnl_pct": 2.103321033210337,
      "type": "cashcow",
      "sector": "公用事业"
    },
    {
      "code": "601088",
      "name": "中国神华",
      "shares": 200,
      "avg_cost": 45.59,
      "cost": 9118.0,
      "current_price": 47.29,
      "market_value": 9458.0,
      "pnl": 340.0,
      "pnl_pct": 3.728887914016221,
      "type": "cashcow",
      "sector": "能源"
    }
  ],
  "trades": [
    {
      "date": "2026-05-28",
      "action": "SELL",
      "code": "603986",
      "name": "兆易创新",
      "shares": 200,
      "price": 483.79,
      "amount": 96758.0,
      "commission": 5.0
    },
    {
      "date": "2026-05-22",
      "action": "BUY",
      "code": "603986",
      "name": "兆易创新",
      "shares": 100,
      "price": 445.02,
      "amount": 44502.0,
      "commission": 5.0
    },
    {
      "date": "2026-05-22",
      "action": "BUY",
      "code": "603986",
      "name": "兆易创新",
      "shares": 100,
      "price": 445.02,
      "amount": 44502.0,
      "commission": 5.0
    },
    {
      "date": "2026-05-12",
      "action": "BUY",
      "code": "600900",
      "name": "长江电力",
      "shares": 200,
      "price": 27.2,
      "amount": 5440.0,
      "commission": 5.0
    },
    {
      "date": "2026-05-12",
      "action": "BUY",
      "code": "601088",
      "name": "中国神华",
      "shares": 200,
      "price": 45.59,
      "amount": 9118.0,
      "commission": 5.0
    },
    {
      "date": "2026-05-08",
      "action": "BUY",
      "code": "600900",
      "name": "长江电力",
      "shares": 200,
      "price": 27.0,
      "amount": 5400.0,
      "commission": 5.0
    },
    {
      "date": "2026-05-08",
      "action": "BUY",
      "code": "600406",
      "name": "国电南瑞",
      "shares": 200,
      "price": 25.9,
      "amount": 5180.0,
      "commission": 5.0
    }
  ],
  "redlines": [
    {
      "name": "单票≤10%",
      "value": "9.0%",
      "limit": "10%",
      "status": "ok"
    },
    {
      "name": "单行业≤20%",
      "value": "--",
      "limit": "20%",
      "status": "ok"
    },
    {
      "name": "现金≥10%",
      "value": "79.5%",
      "limit": "10%",
      "status": "ok"
    },
    {
      "name": "回撤熔断",
      "value": "0.00%",
      "limit": "15%",
      "status": "ok"
    }
  ]
}