{"updated": "2026-05-29T10:41:24.506590", "data": [{"name": "深证成指", "code": "0.399001", "price": 15820.9, "change_pct": -0.26, "volume": 44848579000.0, "high": null, "low": null, "open": null, "prev_close": 15862.14}, {"name": "创业板指", "code": "0.399006", "price": 4124.58, "change_pct": -0.01, "volume": 2177248300.0, "high": null, "low": null, "open": null, "prev_close": 4124.99}, {"name": "上证指数", "code": "1.000001", "price": 4095.2059, "change_pct": -0.08, "volume": 366083700.0, "high": null, "low": null, "open": null, "prev_close": 4098.48}]}