{"updated": "2026-05-26T14:01:29.031951", "data": [{"name": "深证成指", "code": "0.399001", "price": 15718.17, "change_pct": -0.87, "volume": 67770834900.0, "high": null, "low": null, "open": null, "prev_close": 15856.12}, {"name": "创业板指", "code": "0.399006", "price": 4001.04, "change_pct": -0.5, "volume": 3495350400.0, "high": null, "low": null, "open": null, "prev_close": 4021.15}, {"name": "上证指数", "code": "1.000001", "price": 4114.5899, "change_pct": -0.91, "volume": 535978900.0, "high": null, "low": null, "open": null, "prev_close": 4152.38}]}