{"updated": "2026-06-11T14:44:22.895304", "data": [{"name": "深证成指", "code": "0.399001", "price": 14792.2, "change_pct": -1.08, "volume": 62164623200.0, "high": null, "low": null, "open": null, "prev_close": 14953.7}, {"name": "创业板指", "code": "0.399006", "price": 3792.91, "change_pct": -1.61, "volume": 3017445700.0, "high": null, "low": null, "open": null, "prev_close": 3854.98}, {"name": "上证指数", "code": "1.000001", "price": 3976.2961, "change_pct": -0.42, "volume": 528035500.0, "high": null, "low": null, "open": null, "prev_close": 3993.07}]}