{"updated": "2026-06-22T14:20:18.013967", "data": [{"name": "深证成指", "code": "0.399001", "price": 16306.06, "change_pct": 1.72, "volume": 76300969500.0, "high": null, "low": null, "open": null, "prev_close": 16030.34}, {"name": "创业板指", "code": "0.399006", "price": 4343.56, "change_pct": 2.14, "volume": 5064879200.0, "high": null, "low": null, "open": null, "prev_close": 4252.56}, {"name": "上证指数", "code": "1.000001", "price": 4149.4319, "change_pct": 1.44, "volume": 647576300.0, "high": null, "low": null, "open": null, "prev_close": 4090.53}]}