{"updated": "2026-06-29T13:01:12.646033", "data": [{"name": "深证成指", "code": "0.399001", "price": 15550.24, "change_pct": -1.47, "volume": 58067956700.0, "high": null, "low": null, "open": null, "prev_close": 15782.24}, {"name": "创业板指", "code": "0.399006", "price": 4128.02, "change_pct": -1.58, "volume": 3543504100.0, "high": null, "low": null, "open": null, "prev_close": 4194.29}, {"name": "上证指数", "code": "1.000001", "price": 4026.3734, "change_pct": -0.02, "volume": 471314000.0, "high": null, "low": null, "open": null, "prev_close": 4027.18}]}