{"updated": "2026-06-24T10:50:17.199919", "data": [{"name": "深证成指", "code": "0.399001", "price": 15790.45, "change_pct": -0.4, "volume": 43339617800.0, "high": null, "low": null, "open": null, "prev_close": 15853.87}, {"name": "创业板指", "code": "0.399006", "price": 4181.31, "change_pct": -0.26, "volume": 2424932200.0, "high": null, "low": null, "open": null, "prev_close": 4192.21}, {"name": "上证指数", "code": "1.000001", "price": 4079.9352, "change_pct": -0.64, "volume": 359790400.0, "high": null, "low": null, "open": null, "prev_close": 4106.21}]}