{"updated": "2026-07-03T14:51:08.346319", "data": [{"name": "深证成指", "code": "0.399001", "price": 15617.82, "change_pct": 0.77, "volume": 74832017700.0, "high": null, "low": null, "open": null, "prev_close": 15498.48}, {"name": "创业板指", "code": "0.399006", "price": 4026.27, "change_pct": 0.22, "volume": 4309210000.0, "high": null, "low": null, "open": null, "prev_close": 4017.43}, {"name": "上证指数", "code": "1.000001", "price": 4049.1393, "change_pct": 0.5, "volume": 574506000.0, "high": null, "low": null, "open": null, "prev_close": 4028.99}]}