{"updated": "2026-07-06T11:40:59.352821", "data": [{"id": 7063, "title": "威胜控股午前涨超9% 附属中标墨西哥CFE年度智能电表招标", "source": "新浪港股", "url": "https://finance.sina.com.cn/stock/hkstock/marketalerts/2026-07-06/doc-inifvuxz8730011.shtml", "category": "财经综合", "published_at": "2026-07-06", "fetched_at": "2026-07-06 03:40:59"}, {"id": 7064, "title": "电力设备股午前走强 威胜控股涨超9%东方电气涨超8%", "source": "新浪港股", "url": "https://finance.sina.com.cn/stock/hkstock/marketalerts/2026-07-06/doc-inifvuxz8728832.shtml", "category": "财经综合", "published_at": "2026-07-06", "fetched_at": "2026-07-06 03:40:59"}, {"id": 7061, "title": "光大期货0706黄金点评：短期黄金止跌回稳，本周关注美联储会议纪要", "source": "市场资讯", "url": "https://finance.sina.com.cn/money/nmetal/hjzx/2026-07-06/doc-inifvuxz8719241.shtml", "category": "海外市场", "published_at": "2026-07-06", "fetched_at": "2026-07-06 03:31:08"}, {"id": 7062, "title": "ST星农、ST万邦、ST龙大，涨停！", "source": "界面新闻", "url": "https://finance.sina.com.cn/stock/roll/2026-07-06/doc-inifvuye8551228.shtml", "category": "市场行情", "published_at": "2026-07-06", "fetched_at": "2026-07-06 03:31:08"}, {"id": 7050, "title": "王欣获批担任现代财险总经理助理", "source": "金融一线", "url": "https://finance.sina.com.cn/jryx/hm/2026-07-06/doc-inifvqsa2067961.shtml", "category": "财经综合", "published_at": "2026-07-06", "fetched_at": "2026-07-06 03:21:13"}, {"id": 7051, "title": "长十乙发射定档，千帆卫星总数升至238颗！华宝基金通用航空ETF（159231）跌2.81%，资金持续净申购300万份", "source": "新浪基金", "url": "https://finance.sina.com.cn/money/fund/etf/2026-07-06/doc-inifvqsa2067368.shtml", "category": "前沿科技", "published_at": "2026-07-06", "fetched_at": "2026-07-06 03:21:13"}, {"id": 7052, "title": "林海涛获批担任英大泰和财险副总经理", "source": "金融一线", "url": "https://finance.sina.com.cn/jryx/hm/2026-07-06/doc-inifvqsh8672476.shtml", "category": "财经综合", "published_at": "2026-07-06", "fetched_at": "2026-07-06 03:21:13"}, {"id": 7053, "title": "万小亮获批担任阳光消费副总经理", "source": "金融一线", "url": "https://finance.sina.com.cn/jryx/hm/2026-07-06/doc-inifvqsa2066404.shtml", "category": "财经综合", "published_at": "2026-07-06", "fetched_at": "2026-07-06 03:21:13"}, {"id": 7054, "title": "闫春仲获批担任民生银行信用卡中心合规官", "source": "金融一线", "url": "https://finance.sina.com.cn/jryx/hm/2026-07-06/doc-inifvqsa2065488.shtml", "category": "财经综合", "published_at": "2026-07-06", "fetched_at": "2026-07-06 03:21:13"}, {"id": 7055, "title": "中华人寿获批增资至44亿元", "source": "金融一线", "url": "https://finance.sina.com.cn/jryx/insurance/2026-07-06/doc-inifvqsc8840915.shtml", "category": "财经综合", "published_at": "2026-07-06", "fetched_at": "2026-07-06 03:21:13"}, {"id": 7056, "title": "20260706农牧渔ETF华宝（159275）盘中", "source": "新浪基金", "url": "https://finance.sina.com.cn/money/fund/etf/2026-07-06/doc-inifvqsh8666932.shtml", "category": "财经综合", "published_at": "2026-07-06", "fetched_at": "2026-07-06 03:21:13"}, {"id": 7057, "title": "中国儒意盘中涨超6% 将成为微信Agent在影院赛道独家首批合作方", "source": "新浪港股", "url": "https://finance.sina.com.cn/stock/hkstock/marketalerts/2026-07-06/doc-inifvqsa2060078.shtml", "category": "财经综合", "published_at": "2026-07-06", "fetched_at": "2026-07-06 03:21:13"}, {"id": 7058, "title": "天府银行6.64%股权将拍卖！第五大股东被动\"出局\"、地方国资会否接盘", "source": "市场资讯", "url": "https://finance.sina.com.cn/money/bank/gsdt/2026-07-06/doc-inifvqsa2061347.shtml", "category": "财经综合", "published_at": "2026-07-06", "fetched_at": "2026-07-06 03:21:13"}, {"id": 7059, "title": "“摘星脱帽”后3连板！000656，一字涨停！", "source": "市场资讯", "url": "https://finance.sina.com.cn/wm/2026-07-06/doc-inifvqsa2054553.shtml", "category": "市场行情", "published_at": "2026-07-06", "fetched_at": "2026-07-06 03:21:13"}, {"id": 7060, "title": "冲上热搜！银行领导被曝见不得员工准时下班", "source": "市场资讯", "url": "https://finance.sina.com.cn/money/bank/bank_hydt/2026-07-06/doc-inifvqsh8664392.shtml", "category": "财经综合", "published_at": "2026-07-06", "fetched_at": "2026-07-06 03:21:13"}, {"id": 7046, "title": "李俊杰任上海市委金融办常务副主任", "source": "金融一线", "url": "https://finance.sina.com.cn/jryx/bank/2026-07-06/doc-inifvqsa2058858.shtml", "category": "财经综合", "published_at": "2026-07-06", "fetched_at": "2026-07-06 03:10:17"}, {"id": 7047, "title": "远大医药早盘涨超4% 合作伙伴全球首创核药TLX591-Tx再传佳音", "source": "新浪港股", "url": "https://finance.sina.com.cn/stock/hkstock/marketalerts/2026-07-06/doc-inifvqsa2058806.shtml", "category": "财经综合", "published_at": "2026-07-06", "fetched_at": "2026-07-06 03:10:17"}, {"id": 7048, "title": "创新药走出独立行情！场内唯一药ETF突破年线，港股通创新药涨势如虹，520880盘中冲刺7%！", "source": "新浪基金", "url": "https://finance.sina.com.cn/money/fund/etf/2026-07-06/doc-inifvqsh8656681.shtml", "category": "市场行情", "published_at": "2026-07-06", "fetched_at": "2026-07-06 03:10:17"}, {"id": 7049, "title": "688197，“20cm”涨停", "source": "上海证券报", "url": "https://finance.sina.com.cn/stock/roll/2026-07-06/doc-inifvqsh8658275.shtml", "category": "市场行情", "published_at": "2026-07-06", "fetched_at": "2026-07-06 03:10:17"}, {"id": 7040, "title": "“韬定律”V2版正式发布！先进封装国产突围加速！电子ETF随市回调，机构：电子板块业绩增速较高！", "source": "新浪基金", "url": "https://finance.sina.com.cn/money/fund/etf/2026-07-06/doc-inifvqsa2051668.shtml", "category": "财经综合", "published_at": "2026-07-06", "fetched_at": "2026-07-06 03:01:14"}, {"id": 7041, "title": "快手-W早盘涨逾5% 大摩指核心业务隐含估值极具吸引力", "source": "新浪港股", "url": "https://finance.sina.com.cn/stock/hkstock/marketalerts/2026-07-06/doc-inifvqsc8827996.shtml", "category": "财经综合", "published_at": "2026-07-06", "fetched_at": "2026-07-06 03:01:14"}, {"id": 7042, "title": "荃信生物-B盘中涨超8% 公司创新性管线出海授权陆续达成", "source": "新浪港股", "url": "https://finance.sina.com.cn/stock/hkstock/marketalerts/2026-07-06/doc-inifvqsh8651415.shtml", "category": "财经综合", "published_at": "2026-07-06", "fetched_at": "2026-07-06 03:01:14"}, {"id": 7043, "title": "美图公司盘中涨超6% 创始人吴欣鸿再增持160万股公司股份", "source": "新浪港股", "url": "https://finance.sina.com.cn/stock/hkstock/marketalerts/2026-07-06/doc-inifvqsc8823471.shtml", "category": "财经综合", "published_at": "2026-07-06", "fetched_at": "2026-07-06 03:01:14"}, {"id": 7044, "title": "创新药概念股延续涨势 中国生物制药涨逾11%诺诚健华涨逾10%", "source": "新浪港股", "url": "https://finance.sina.com.cn/stock/hkstock/marketalerts/2026-07-06/doc-inifvqsh8646361.shtml", "category": "财经综合", "published_at": "2026-07-06", "fetched_at": "2026-07-06 03:01:14"}, {"id": 7045, "title": "600172，直线拉涨停！71万手封板", "source": "滚动播报", "url": "https://finance.sina.com.cn/money/fund/etf/2026-07-06/doc-inifvqsa2047516.shtml", "category": "市场行情", "published_at": "2026-07-06", "fetched_at": "2026-07-06 03:01:14"}, {"id": 7026, "title": "大厂AI逻辑持续修复，腾讯WorkBuddy爆了，快手可灵独立商业化开启，低位港股互联网ETF华宝再涨2%冲击3连阳", "source": "新浪基金", "url": "https://finance.sina.com.cn/money/fund/etf/2026-07-06/doc-inifvqsc8820407.shtml", "category": "AI模型", "published_at": "2026-07-06", "fetched_at": "2026-07-06 02:50:24"}, {"id": 7027, "title": "光大期货：7月6日软商品日报", "source": "市场资讯", "url": "https://finance.sina.com.cn/money/future/fmnews/2026-07-06/doc-inifvqsc8819650.shtml", "category": "财经综合", "published_at": "2026-07-06", "fetched_at": "2026-07-06 02:50:24"}, {"id": 7028, "title": "光大期货：7月6日有色金属日报", "source": "市场资讯", "url": "https://finance.sina.com.cn/money/future/fmnews/2026-07-06/doc-inifvqsh8642967.shtml", "category": "财经综合", "published_at": "2026-07-06", "fetched_at": "2026-07-06 02:50:24"}, {"id": 7029, "title": "冲高回落，科技牛回头？科技ETF华宝（515000）跌超2%！江波龙绩后大涨，机构建议紧盯中报催化", "source": "新浪基金", "url": "https://finance.sina.com.cn/money/fund/etf/2026-07-06/doc-inifvqsh8642461.shtml", "category": "财经综合", "published_at": "2026-07-06", "fetched_at": "2026-07-06 02:50:24"}, {"id": 7030, "title": "光大期货：7月6日金融日报", "source": "市场资讯", "url": "https://finance.sina.com.cn/money/future/fmnews/2026-07-06/doc-inifvqsf1866173.shtml", "category": "财经综合", "published_at": "2026-07-06", "fetched_at": "2026-07-06 02:50:24"}]}