{"updated": "2026-07-06T11:10:17.817027", "data": [{"id": 7046, "title": "李俊杰任上海市委金融办常务副主任", "source": "金融一线", "url": "https://finance.sina.com.cn/jryx/bank/2026-07-06/doc-inifvqsa2058858.shtml", "category": "财经综合", "published_at": "2026-07-06", "fetched_at": "2026-07-06 03:10:17"}, {"id": 7047, "title": "远大医药早盘涨超4% 合作伙伴全球首创核药TLX591-Tx再传佳音", "source": "新浪港股", "url": "https://finance.sina.com.cn/stock/hkstock/marketalerts/2026-07-06/doc-inifvqsa2058806.shtml", "category": "财经综合", "published_at": "2026-07-06", "fetched_at": "2026-07-06 03:10:17"}, {"id": 7048, "title": "创新药走出独立行情！场内唯一药ETF突破年线，港股通创新药涨势如虹，520880盘中冲刺7%！", "source": "新浪基金", "url": "https://finance.sina.com.cn/money/fund/etf/2026-07-06/doc-inifvqsh8656681.shtml", "category": "市场行情", "published_at": "2026-07-06", "fetched_at": "2026-07-06 03:10:17"}, {"id": 7049, "title": "688197，“20cm”涨停", "source": "上海证券报", "url": "https://finance.sina.com.cn/stock/roll/2026-07-06/doc-inifvqsh8658275.shtml", "category": "市场行情", "published_at": "2026-07-06", "fetched_at": "2026-07-06 03:10:17"}, {"id": 7040, "title": "“韬定律”V2版正式发布！先进封装国产突围加速！电子ETF随市回调，机构：电子板块业绩增速较高！", "source": "新浪基金", "url": "https://finance.sina.com.cn/money/fund/etf/2026-07-06/doc-inifvqsa2051668.shtml", "category": "财经综合", "published_at": "2026-07-06", "fetched_at": "2026-07-06 03:01:14"}, {"id": 7041, "title": "快手-W早盘涨逾5% 大摩指核心业务隐含估值极具吸引力", "source": "新浪港股", "url": "https://finance.sina.com.cn/stock/hkstock/marketalerts/2026-07-06/doc-inifvqsc8827996.shtml", "category": "财经综合", "published_at": "2026-07-06", "fetched_at": "2026-07-06 03:01:14"}, {"id": 7042, "title": "荃信生物-B盘中涨超8% 公司创新性管线出海授权陆续达成", "source": "新浪港股", "url": "https://finance.sina.com.cn/stock/hkstock/marketalerts/2026-07-06/doc-inifvqsh8651415.shtml", "category": "财经综合", "published_at": "2026-07-06", "fetched_at": "2026-07-06 03:01:14"}, {"id": 7043, "title": "美图公司盘中涨超6% 创始人吴欣鸿再增持160万股公司股份", "source": "新浪港股", "url": "https://finance.sina.com.cn/stock/hkstock/marketalerts/2026-07-06/doc-inifvqsc8823471.shtml", "category": "财经综合", "published_at": "2026-07-06", "fetched_at": "2026-07-06 03:01:14"}, {"id": 7044, "title": "创新药概念股延续涨势 中国生物制药涨逾11%诺诚健华涨逾10%", "source": "新浪港股", "url": "https://finance.sina.com.cn/stock/hkstock/marketalerts/2026-07-06/doc-inifvqsh8646361.shtml", "category": "财经综合", "published_at": "2026-07-06", "fetched_at": "2026-07-06 03:01:14"}, {"id": 7045, "title": "600172，直线拉涨停！71万手封板", "source": "滚动播报", "url": "https://finance.sina.com.cn/money/fund/etf/2026-07-06/doc-inifvqsa2047516.shtml", "category": "市场行情", "published_at": "2026-07-06", "fetched_at": "2026-07-06 03:01:14"}, {"id": 7026, "title": "大厂AI逻辑持续修复，腾讯WorkBuddy爆了，快手可灵独立商业化开启，低位港股互联网ETF华宝再涨2%冲击3连阳", "source": "新浪基金", "url": "https://finance.sina.com.cn/money/fund/etf/2026-07-06/doc-inifvqsc8820407.shtml", "category": "AI模型", "published_at": "2026-07-06", "fetched_at": "2026-07-06 02:50:24"}, {"id": 7027, "title": "光大期货：7月6日软商品日报", "source": "市场资讯", "url": "https://finance.sina.com.cn/money/future/fmnews/2026-07-06/doc-inifvqsc8819650.shtml", "category": "财经综合", "published_at": "2026-07-06", "fetched_at": "2026-07-06 02:50:24"}, {"id": 7028, "title": "光大期货：7月6日有色金属日报", "source": "市场资讯", "url": "https://finance.sina.com.cn/money/future/fmnews/2026-07-06/doc-inifvqsh8642967.shtml", "category": "财经综合", "published_at": "2026-07-06", "fetched_at": "2026-07-06 02:50:24"}, {"id": 7029, "title": "冲高回落，科技牛回头？科技ETF华宝（515000）跌超2%！江波龙绩后大涨，机构建议紧盯中报催化", "source": "新浪基金", "url": "https://finance.sina.com.cn/money/fund/etf/2026-07-06/doc-inifvqsh8642461.shtml", "category": "财经综合", "published_at": "2026-07-06", "fetched_at": "2026-07-06 02:50:24"}, {"id": 7030, "title": "光大期货：7月6日金融日报", "source": "市场资讯", "url": "https://finance.sina.com.cn/money/future/fmnews/2026-07-06/doc-inifvqsf1866173.shtml", "category": "财经综合", "published_at": "2026-07-06", "fetched_at": "2026-07-06 02:50:24"}, {"id": 7031, "title": "东方航空早盘涨超3% 截至6月末累计回购1505.21万股A股", "source": "新浪港股", "url": "https://finance.sina.com.cn/stock/hkstock/marketalerts/2026-07-06/doc-inifvqsc8818504.shtml", "category": "市场行情", "published_at": "2026-07-06", "fetched_at": "2026-07-06 02:50:24"}, {"id": 7032, "title": "光大期货：7月6日矿钢煤焦日报", "source": "市场资讯", "url": "https://finance.sina.com.cn/money/future/fmnews/2026-07-06/doc-inifvqsa2040825.shtml", "category": "财经综合", "published_at": "2026-07-06", "fetched_at": "2026-07-06 02:50:24"}, {"id": 7033, "title": "光大期货：7月6日能源化工日报", "source": "市场资讯", "url": "https://finance.sina.com.cn/money/future/fmnews/2026-07-06/doc-inifvqsa2040220.shtml", "category": "财经综合", "published_at": "2026-07-06", "fetched_at": "2026-07-06 02:50:24"}, {"id": 7034, "title": "特朗普赴土耳其参加北约峰会日程：将会见埃尔多安、吕特、泽连斯基等", "source": "环球市场播报", "url": "https://finance.sina.com.cn/stock/usstock/c/2026-07-06/doc-inifvqsa2039907.shtml", "category": "财经综合", "published_at": "2026-07-06", "fetched_at": "2026-07-06 02:50:24"}, {"id": 7035, "title": "挚达科技盘中涨超27% 积极布局充电机器人业务", "source": "新浪港股", "url": "https://finance.sina.com.cn/stock/hkstock/marketalerts/2026-07-06/doc-inifvqsc8816976.shtml", "category": "前沿科技", "published_at": "2026-07-06", "fetched_at": "2026-07-06 02:50:24"}, {"id": 7036, "title": "光大期货：7月6日农产品日报", "source": "市场资讯", "url": "https://finance.sina.com.cn/money/future/fmnews/2026-07-06/doc-inifvqsc8816896.shtml", "category": "财经综合", "published_at": "2026-07-06", "fetched_at": "2026-07-06 02:50:24"}, {"id": 7037, "title": "7月生猪出栏计划环比微增，但出栏节奏或有所放缓", "source": "市场资讯", "url": "https://finance.sina.com.cn/money/future/fmnews/2026-07-06/doc-inifvqsc8814983.shtml", "category": "财经综合", "published_at": "2026-07-06", "fetched_at": "2026-07-06 02:50:24"}, {"id": 7038, "title": "花生半年度总结：上半年区域价差收窄 下半年供应压力或减小", "source": "市场资讯", "url": "https://finance.sina.com.cn/money/future/fmnews/2026-07-06/doc-inifvqsc8814061.shtml", "category": "财经综合", "published_at": "2026-07-06", "fetched_at": "2026-07-06 02:50:24"}, {"id": 7039, "title": "长安期货范磊：商品属性重回主导，关注油价阶段下行", "source": "市场资讯", "url": "https://finance.sina.com.cn/money/future/fmnews/2026-07-06/doc-inifvqsc8812999.shtml", "category": "财经综合", "published_at": "2026-07-06", "fetched_at": "2026-07-06 02:50:24"}, {"id": 7021, "title": "“韬定律”V2版发布！规模最大港股通信息技术ETF华宝（159131）跌超3%，硬科技布局窗口还在吗？", "source": "新浪基金", "url": "https://finance.sina.com.cn/money/fund/etf/2026-07-06/doc-inifvqsf1851245.shtml", "category": "财经综合", "published_at": "2026-07-06", "fetched_at": "2026-07-06 02:40:48"}, {"id": 7022, "title": "逾32万手封单！1分钟，直线涨停", "source": "中国证券报", "url": "https://finance.sina.com.cn/stock/roll/2026-07-06/doc-inifvqsa2034003.shtml", "category": "市场行情", "published_at": "2026-07-06", "fetched_at": "2026-07-06 02:40:48"}, {"id": 7023, "title": "宁德时代投资新西兰一家生物基石墨技术研发公司", "source": "环球市场播报", "url": "https://finance.sina.com.cn/stock/usstock/c/2026-07-06/doc-inifvqsa2029065.shtml", "category": "财经综合", "published_at": "2026-07-06", "fetched_at": "2026-07-06 02:40:48"}, {"id": 7024, "title": "五倍大牛股，跌停", "source": "上海证券报", "url": "https://finance.sina.com.cn/stock/relnews/2026-07-06/doc-inifvqsc8808168.shtml", "category": "市场行情", "published_at": "2026-07-06", "fetched_at": "2026-07-06 02:40:48"}, {"id": 7025, "title": "港股光通信、PCB概念股集体下挫，长飞光纤光缆跌逾16%，建滔积层板跌超13%", "source": "新浪港股", "url": "https://finance.sina.com.cn/stock/hkstock/2026-07-06/doc-inifvqsh8624691.shtml", "category": "财经综合", "published_at": "2026-07-06", "fetched_at": "2026-07-06 02:40:48"}, {"id": 7016, "title": "双创50，何以跑赢科创50、创业板50？", "source": "新浪基金", "url": "https://finance.sina.com.cn/money/fund/etf/2026-07-06/doc-inifvqsc8801008.shtml", "category": "市场行情", "published_at": "2026-07-06", "fetched_at": "2026-07-06 02:31:05"}]}